langchain_prefid/__init__.py
langchain_prefid/tools.py
langchain_prefid-0.2.0.dist-info/METADATA
langchain_prefid-0.2.0.dist-info/WHEEL
langchain_prefid-0.2.0.dist-info/top_level.txt
langchain_prefid-0.2.0.dist-info/RECORD
