Metadata-Version: 2.4
Name: langchain-prefid
Version: 0.2.0
Summary: LangChain integration for PrefID - Preference-aware AI agents
Author-email: PrefID Team <sriram.srinivasdesikan@gmail.com>
License: MIT
Project-URL: Homepage, https://prefid.in
Project-URL: Documentation, https://docs.prefid.in
Project-URL: Repository, https://github.com/Talentxmdu/PrefID
Project-URL: Bug Tracker, https://github.com/Talentxmdu/PrefID/issues
Keywords: langchain,prefid,preferences,ai,agents,llm
Classifier: Development Status :: 4 - Beta
Classifier: Intended Audience :: Developers
Classifier: License :: OSI Approved :: MIT License
Classifier: Programming Language :: Python :: 3
Classifier: Programming Language :: Python :: 3.9
Classifier: Programming Language :: Python :: 3.10
Classifier: Programming Language :: Python :: 3.11
Classifier: Programming Language :: Python :: 3.12
Requires-Python: >=3.9
Requires-Dist: langchain-core>=0.1.0
Requires-Dist: prefid>=0.2.0
Requires-Dist: pydantic>=2.0.0
Provides-Extra: dev
Requires-Dist: pytest>=7.0; extra == "dev"
Requires-Dist: pytest-asyncio>=0.21.0; extra == "dev"
Requires-Dist: langchain-anthropic>=0.1.0; extra == "dev"
